zam_authentic/__init__.py
zam_authentic/main.py
zam_authentic/locations/__init__.py
zam_authentic/locations/constants.py
zam_authentic/locations/constituencies.py
zam_authentic/locations/districts.py
zam_authentic/locations/get_locations.py
zam_authentic/locations/provinces.py
zam_authentic/locations/towns.py
zam_authentic/locations/wards.py
zam_authentic/nrc_validation/__init__.py
zam_authentic/nrc_validation/constants.py
zam_authentic/nrc_validation/utils.py
zam_authentic/nrc_validation/validate.py
zam_authentic/phone_number_validation/__init__.py
zam_authentic/phone_number_validation/constants.py
zam_authentic/phone_number_validation/validate.py
zam_authentic-0.0.13.dist-info/LICENSE
zam_authentic-0.0.13.dist-info/METADATA
zam_authentic-0.0.13.dist-info/WHEEL
zam_authentic-0.0.13.dist-info/top_level.txt
zam_authentic-0.0.13.dist-info/RECORD
